{"stats":{"minecraft:used":{"minecraft:flint_and_steel":1,"minecraft:rotten_flesh":1,"minecraft:netherrack":193,"minecraft:nether_bricks":196,"minecraft:golden_chestplate":1,"minecraft:nether_brick_stairs":4,"minecraft:obsidian":20,"minecraft:wooden_axe":59,"minecraft:lava_bucket":16,"minecraft:stone_brick_stairs":17,"minecraft:stone_bricks":9,"minecraft:sweet_berries":3,"minecraft:furnace":1,"minecraft:cooked_cod":25,"minecraft:egg":9,"minecraft:cooked_mutton":2,"minecraft:water_bucket":4,"minecraft:cobblestone_stairs":2,"minecraft:oak_planks":2,"minecraft:spruce_chest_boat":1,"minecraft:wooden_pickaxe":3,"minecraft:brown_mushroom":1,"minecraft:crafting_table":4,"minecraft:white_bed":3,"minecraft:dripstone_block":8,"minecraft:diamond_pickaxe":2184,"minecraft:chicken":3,"minecraft:spruce_sapling":4,"minecraft:diamond_sword":46,"minecraft:cobblestone":19,"minecraft:bucket":22,"minecraft:andesite":1},"minecraft:broken":{"minecraft:wooden_axe":1,"minecraft:golden_chestplate":1},"minecraft:crafted":{"minecraft:furnace":1,"minecraft:nether_brick":100,"minecraft:flint_and_steel":1,"minecraft:stone_bricks":64,"minecraft:cooked_cod":33,"minecraft:emerald":5,"minecraft:crafting_table":4,"minecraft:spruce_planks":28,"minecraft:wooden_pickaxe":1,"minecraft:nether_bricks":218,"minecraft:bucket":1,"minecraft:air":0,"minecraft:stone_brick_stairs":20,"minecraft:book":21,"minecraft:paper":63,"minecraft:stick":4,"minecraft:iron_ingot":3,"minecraft:wooden_axe":1,"minecraft:gold_ingot":17,"minecraft:white_bed":1,"minecraft:nether_brick_stairs":4},"minecraft:killed":{"minecraft:skeleton":4,"minecraft:chicken":3,"minecraft:drowned":1,"minecraft:zombie":7},"minecraft:custom":{"minecraft:mob_kills":15,"minecraft:interact_with_crafting_table":31,"minecraft:leave_game":5,"minecraft:time_since_death":177903,"minecraft:climb_one_cm":2761,"minecraft:sprint_one_cm":343518,"minecraft:walk_one_cm":752801,"minecraft:drop":23,"minecraft:talked_to_villager":4,"minecraft:play_time":177903,"minecraft:sneak_time":2256,"minecraft:walk_under_water_one_cm":279709,"minecraft:boat_one_cm":64596,"minecraft:interact_with_lectern":13,"minecraft:jump":2048,"minecraft:walk_on_water_one_cm":26791,"minecraft:total_world_time":177903,"minecraft:interact_with_furnace":112,"minecraft:traded_with_villager":5,"minecraft:sleep_in_bed":3,"minecraft:time_since_rest":51583,"minecraft:damage_taken":1098,"minecraft:damage_dealt":2444,"minecraft:swim_one_cm":5517,"minecraft:fly_one_cm":260649,"minecraft:open_chest":139,"minecraft:crouch_one_cm":5491,"minecraft:fall_one_cm":36173},"minecraft:picked_up":{"minecraft:chicken":3,"minecraft:diamond_sword":1,"minecraft:brown_mushroom":5,"minecraft:gold_block":1,"minecraft:stone_brick_stairs":4,"minecraft:spruce_chest_boat":1,"minecraft:blackstone":5,"minecraft:cracked_stone_bricks":2,"minecraft:diamond_leggings":1,"minecraft:gold_nugget":76,"minecraft:cobbled_deepslate":302,"minecraft:spruce_planks":1,"minecraft:sugar_cane":65,"minecraft:egg":9,"minecraft:raw_iron":3,"minecraft:stick":1,"minecraft:torch":1,"minecraft:fire_charge":1,"minecraft:pointed_dripstone":16,"minecraft:golden_chestplate":1,"minecraft:arrow":3,"minecraft:rotten_flesh":6,"minecraft:nether_bricks":191,"minecraft:diamond_boots":1,"minecraft:obsidian":23,"minecraft:iron_bars":1,"minecraft:white_wool":5,"minecraft:cobblestone":101,"minecraft:magma_block":13,"minecraft:feather":6,"minecraft:andesite":3,"minecraft:flint":1,"minecraft:tuff":18,"minecraft:golden_boots":1,"minecraft:cobblestone_stairs":2,"minecraft:lapis_lazuli":26,"minecraft:dirt":21,"minecraft:cooked_mutton":2,"minecraft:bone":2,"minecraft:stone_bricks":1,"minecraft:oak_planks":2,"minecraft:mossy_stone_brick_stairs":1,"minecraft:sweet_berries":3,"minecraft:stone_brick_slab":4,"minecraft:quartz":22,"minecraft:gravel":25,"minecraft:dripstone_block":8,"minecraft:nether_brick_stairs":4,"minecraft:spruce_sapling":5,"minecraft:white_bed":2,"minecraft:spruce_log":107,"minecraft:crying_obsidian":5,"minecraft:mossy_stone_brick_slab":2,"minecraft:mossy_cobblestone":3,"minecraft:granite":17,"minecraft:gray_wool":2,"minecraft:netherrack":1069,"minecraft:diamond_pickaxe":1},"minecraft:mined":{"minecraft:nether_gold_ore":24,"minecraft:crying_obsidian":5,"minecraft:tuff":27,"minecraft:white_bed":3,"minecraft:mossy_cobblestone":3,"minecraft:cobblestone_stairs":2,"minecraft:obsidian":21,"minecraft:nether_bricks":196,"minecraft:granite":15,"minecraft:grass_block":5,"minecraft:spruce_leaves":5,"minecraft:magma_block":14,"minecraft:iron_ore":3,"minecraft:cobbled_deepslate":2,"minecraft:fire":19,"minecraft:andesite":3,"minecraft:nether_brick_stairs":4,"minecraft:gold_block":1,"minecraft:mossy_stone_brick_stairs":1,"minecraft:iron_bars":1,"minecraft:stone":101,"minecraft:brown_mushroom":3,"minecraft:blackstone":5,"minecraft:stone_brick_slab":3,"minecraft:nether_quartz_ore":22,"minecraft:cobblestone":14,"minecraft:lapis_ore":4,"minecraft:sugar_cane":32,"minecraft:oak_planks":3,"minecraft:sweet_berry_bush":1,"minecraft:spruce_log":109,"minecraft:stone_brick_stairs":4,"minecraft:grass":5,"minecraft:gravel":13,"minecraft:dripstone_block":2,"minecraft:dirt":17,"minecraft:cracked_stone_bricks":1,"minecraft:stone_bricks":1,"minecraft:netherrack":1334,"minecraft:gold_ore":2,"minecraft:deepslate":354},"minecraft:dropped":{"minecraft:feather":3,"minecraft:granite":16,"minecraft:cracked_stone_bricks":2,"minecraft:stick":1,"minecraft:dirt":17,"minecraft:stone_brick_slab":2,"minecraft:gold_ingot":8,"minecraft:pointed_dripstone":16,"minecraft:mossy_stone_brick_slab":1,"minecraft:diamond_sword":1,"minecraft:spruce_planks":1,"minecraft:andesite":2,"minecraft:iron_bars":1}},"DataVersion":3337}